calc/__init__.py
calc/calc.py
calc_porcentagem-0.0.3.dist-info/METADATA
calc_porcentagem-0.0.3.dist-info/WHEEL
calc_porcentagem-0.0.3.dist-info/top_level.txt
calc_porcentagem-0.0.3.dist-info/RECORD
