Metadata-Version: 2.1
Name: calc-porcentagem
Version: 0.0.3
Summary: Pacote de calculo basico de porcentagem
Home-page: 
Author: Anderson Willian
Author-email: anderw1ll@outlook.com
Requires-Python: >=3
